booktest/__init__.py
booktest/__main__.py
booktest/booktest.py
booktest/cli.py
booktest/config/__init__.py
booktest/config/config.py
booktest/config/detection.py
booktest/config/naming.py
booktest/config/selection.py
booktest/core/__init__.py
booktest/core/runs.py
booktest/core/testbook.py
booktest/core/testcaserun.py
booktest/core/testrun.py
booktest/core/tests.py
booktest/core/testsuite.py
booktest/dependencies/__init__.py
booktest/dependencies/cache.py
booktest/dependencies/dependencies.py
booktest/dependencies/memory.py
booktest/llm/__init__.py
booktest/llm/llm.py
booktest/llm/llm_review.py
booktest/llm/tokenizer.py
booktest/migration/__init__.py
booktest/migration/migrate.py
booktest/reporting/__init__.py
booktest/reporting/books.py
booktest/reporting/colors.py
booktest/reporting/output.py
booktest/reporting/reports.py
booktest/reporting/review.py
booktest/reporting/testing.py
booktest/snapshots/__init__.py
booktest/snapshots/env.py
booktest/snapshots/functions.py
booktest/snapshots/httpx.py
booktest/snapshots/requests.py
booktest/snapshots/snapshots.py
booktest/snapshots/storage.py
booktest/utils/__init__.py
booktest/utils/coroutines.py
booktest/utils/setup.py
booktest/utils/utils.py
booktest-1.1.0.dist-info/METADATA
booktest-1.1.0.dist-info/WHEEL
booktest-1.1.0.dist-info/entry_points.txt
booktest-1.1.0.dist-info/licenses/LICENSE
booktest-1.1.0.dist-info/RECORD
