Metadata-Version: 2.4
Name: booktest
Version: 1.1.0
Summary: Booktest is a snapshot testing library for review driven testing.
License-File: LICENSE
Author: Antti Rauhala
Author-email: antti@lumoa.me
Requires-Python: >=3.10,<4.0
Classifier: Development Status :: 5 - Production/Stable
Classifier: License :: OSI Approved :: MIT License
Classifier: Operating System :: OS Independent
Classifier: Programming Language :: Python :: 3
Classifier: Programming Language :: Python :: 3.10
Classifier: Programming Language :: Python :: 3.11
Classifier: Programming Language :: Python :: 3.12
Classifier: Programming Language :: Python :: 3.13
Classifier: Programming Language :: Python :: 3.14
Requires-Dist: argcomplete (>=3.0.0,<4.0.0)
Requires-Dist: coverage (>=6.5.0,<7.0.0)
Requires-Dist: httpx (>=0.27.0,<0.28.0)
Requires-Dist: pandas (>=2.0.0,<3.0.0)
Requires-Dist: psutil (>=6.1.1,<7.0.0)
Requires-Dist: requests (>=2.31.0,<3.0.0)
Project-URL: Homepage, https://github.com/lumoa-oss/booktest
Project-URL: Repository, https://github.com/lumoa-oss/booktest
